{
  "model_type": "query_tsvit",
  "dataset_npz": "artifacts/patches_clean/train_cnn_transformer_15x15.npz",
  "normalization_json": "artifacts/normalization/train_patch_band_stats.json",
  "split_csv": "artifacts/splits/train_val_split.csv",
  "output_dir": "artifacts/models/c28_tsvit_local_smoke",
  "seed": 42,
  "batch_size": 8,
  "epochs": 1,
  "learning_rate": 0.0003,
  "weight_decay": 0.03,
  "num_workers": 0,
  "device": "cpu",
  "amp": false,
  "gradient_accumulation_steps": 1,
  "clip_grad_norm": 1.0,
  "scheduler": "cosine",
  "warmup_epochs": 1,
  "early_stopping_patience": 1,
  "save_best_only": true,
  "stage_loss_weight": 0.6,
  "rice_stage_loss_only": true,
  "label_smoothing": 0.0,
  "stage_sequence_loss_weight": 0.05,
  "stage_max_forward_step": 1.5,
  "stage_postprocess": "transition_viterbi",
  "include_valid_mask_as_channels": true,
  "random_time_shift_days": 0,
  "query_doy_dropout_prob": 0.0,
  "time_doy_dropout_prob": 0.0,
  "min_lr": 0.0,
  "checkpoint_metric": "val_competition_score",
  "tie_breaker_metric": "val_loss",
  "model": {
    "in_channels": 24,
    "patch_size": 15,
    "token_patch_size": 3,
    "transformer_dim": 320,
    "temporal_layers": 6,
    "spatial_layers": 6,
    "attention_heads": 8,
    "mlp_ratio": 4.0,
    "dropout": 0.15,
    "num_crop_classes": 3,
    "num_phenophase_classes": 7,
    "use_query_doy": true,
    "use_time_doy": true,
    "time_encoding_type": "fourier",
    "query_encoding_type": "fourier",
    "time_encoding_harmonics": 8,
    "use_relative_query_bias": true
  },
  "selection_rule": "Local smoke test for C28 TSViT on CPU to validate training/inference plumbing before Colab."
}
